configlines/__init__.py
configlines/parsers.py
configlines/tests/__init__.py
configlines/tests/data1.cfg
configlines/tests/data2.cfg
configlines/tests/data3.cfg
configlines/tests/test_parsers.py
configlines-0.3.dist-info/METADATA
configlines-0.3.dist-info/RECORD
configlines-0.3.dist-info/WHEEL
configlines-0.3.dist-info/top_level.txt
